redlibssh2.libs/libssh2-41b31d69.so.1.0.1
redlibssh2.libs/libkeyutils-a0133cb5.so.1.5
redlibssh2.libs/libkrb5-9480970b.so.3.3
redlibssh2.libs/libssl-bcb0479a.so.1.0.2k
redlibssh2.libs/libpcre-863f8bd5.so.1.2.0
redlibssh2.libs/libcom_err-f788d215.so.2.1
redlibssh2.libs/libcrypto-d590720d.so.1.0.2k
redlibssh2.libs/libkrb5support-ff900cbb.so.0.1
redlibssh2.libs/libgssapi_krb5-a7735118.so.2.2
redlibssh2.libs/libselinux-c9aa910a.so.1
redlibssh2.libs/libk5crypto-19d2ee81.so.3.1
redlibssh2-2.1.5.post1.dist-info/METADATA
redlibssh2-2.1.5.post1.dist-info/RECORD
redlibssh2-2.1.5.post1.dist-info/LICENSE
redlibssh2-2.1.5.post1.dist-info/top_level.txt
redlibssh2-2.1.5.post1.dist-info/WHEEL
redlibssh2-2.1.5.post1.dist-info/COPYING
ssh2/error_codes.pxd
ssh2/agent.cpython-39-i386-linux-gnu.so
ssh2/agent.pxd
ssh2/__init__.py
ssh2/utils.pyx
ssh2/utils.cpython-39-i386-linux-gnu.so
ssh2/error_codes.cpython-39-i386-linux-gnu.so
ssh2/knownhost.pxd
ssh2/publickey.pyx
ssh2/sftp_handle.c
ssh2/sftp.pxd
ssh2/tunnel.pxd
ssh2/utils.c
ssh2/pkey.cpython-39-i386-linux-gnu.so
ssh2/fileinfo.c
ssh2/sftp_handle.pxd
ssh2/tunnel.cpython-39-i386-linux-gnu.so
ssh2/listener.cpython-39-i386-linux-gnu.so
ssh2/tunnel.c
ssh2/pkey.pxd
ssh2/channel.cpython-39-i386-linux-gnu.so
ssh2/session.pyx
ssh2/libssh2_enums.c
ssh2/exceptions.pyx
ssh2/listener.pxd
ssh2/publickey.cpython-39-i386-linux-gnu.so
ssh2/publickey.pxd
ssh2/fileinfo.cpython-39-i386-linux-gnu.so
ssh2/channel.pxd
ssh2/sftp.pyx
ssh2/libssh2_enums.pyx
ssh2/c_ssh2.pxd
ssh2/_version.py
ssh2/fileinfo.pxd
ssh2/pkey.c
ssh2/listener.pyx
ssh2/channel.c
ssh2/knownhost.c
ssh2/sftp_handle.pyx
ssh2/listener.c
ssh2/tunnel.pyx
ssh2/publickey.c
ssh2/exceptions.c
ssh2/session.cpython-39-i386-linux-gnu.so
ssh2/sftp_handle.cpython-39-i386-linux-gnu.so
ssh2/statinfo.pyx
ssh2/knownhost.cpython-39-i386-linux-gnu.so
ssh2/utils.pxd
ssh2/pkey.pyx
ssh2/channel.pyx
ssh2/c_stat.pxd
ssh2/statinfo.c
ssh2/libssh2_enums.cpython-39-i386-linux-gnu.so
ssh2/knownhost.pyx
ssh2/session.c
ssh2/sftp.cpython-39-i386-linux-gnu.so
ssh2/statinfo.pxd
ssh2/c_sftp.pxd
ssh2/error_codes.pyx
ssh2/statinfo.cpython-39-i386-linux-gnu.so
ssh2/session.pxd
ssh2/agent.c
